vigi/__init__.py
vigi/__main__.py
vigi/__version__.py
vigi/base_manage.py
vigi/chat_handler.py
vigi/chat_manage.py
vigi/config.py
vigi/consoleUI.py
vigi/convo_manage.py
vigi/corefunctions.py
vigi/default_handler.py
vigi/handler.py
vigi/hold_data.py
vigi/hub_manager.py
vigi/readme.md
vigi/redme.md
vigi/repl_handler.py
vigi/requirements.txt
vigi/start.py
vigi/temp.md
vigi/temp_delete.py
vigi/tools_and_personas.py
vigi/zsh_bash.py
vigi/developerch/api.py
vigi/developerch/main.py
vigi/developerch/prompts.py
vigi/developerch/utils.py
vigi/docker_part/config.py
vigi/docker_part/docker_main.py
vigi/docker_part/docker_project_creator.py
vigi/docker_part/main.py
vigi/docker_part/test.py
vigi/shell_part/__init__.py
vigi/shell_part/agents.py
vigi/shell_part/graph.py
vigi/shell_part/main.py
vigi/shell_part/state.py
vigi/shell_smart/cmd_gen_prompts.py
vigi/shell_smart/config.py
vigi/shell_smart/gemini_interface.py
vigi/shell_smart/shell_main.py
vigi/shell_smart/utils.py
vigilinux-2.0.0.dist-info/METADATA
vigilinux-2.0.0.dist-info/WHEEL
vigilinux-2.0.0.dist-info/entry_points.txt
vigilinux-2.0.0.dist-info/RECORD
